dblinter/__init__.py
dblinter/__main__.py
dblinter/configuration.py
dblinter/configuration_model.py
dblinter/database_connection.py
dblinter/default_config.yaml
dblinter/doc/BASE001-HowManyTableWithoutPrimaryKey.md
dblinter/doc/CLUSTER001-MaxConnectionsByWorkMemIsNotLargerThanMemory.md
dblinter/doc/TABLE001-TableWithoutPrimaryKey.md
dblinter/function_library.py
dblinter/rules/B001/HowManyTableWithoutPrimaryKey.py
dblinter/rules/B002/HowManyRedudantIndex.py
dblinter/rules/B003/HowManyTableWithoutIndexOnFk.py
dblinter/rules/B004/HowManyUnusedIndex.py
dblinter/rules/B005/UnsecuredPublicSchema.py
dblinter/rules/B006/HowManyTablesWithUppercase.py
dblinter/rules/C001/MaxConnectionsByWorkMemIsNotLargerThanMemory.py
dblinter/rules/C002/PgHbaEntriesWithMethodTrustOrPasswordShouldNotExists.py
dblinter/rules/C003/PasswordEncryptionIsMd5.py
dblinter/rules/S001/SchemaWithDefaultRoleNotGranted.py
dblinter/rules/S002/SchemaPrefixedOrSuffixedWithEnvt.py
dblinter/rules/T001/TableWithoutPrimaryKey.py
dblinter/rules/T002/TableWithRedundantIndex.py
dblinter/rules/T003/TableWithFkNotIndexed.py
dblinter/rules/T004/TableWithUnusedIndex.py
dblinter/rules/T005/TableWithPotentialMissingIdx.py
dblinter/rules/T006/TableWithUppercase.py
dblinter/rules/T007/TableWithFkOutsideSchema.py
dblinter/rules/T008/TableWithFkMismatch.py
dblinter/rules/T009/TableWithRoleNotGranted.py
dblinter/rules/T010/ReservedKeyWord.py
dblinter/rules/T012/TableWithSensibleColumn.py
dblinter/sarif_document.py
dblinter/scan.py
dblinter-0.5.6.dist-info/METADATA
dblinter-0.5.6.dist-info/WHEEL
dblinter-0.5.6.dist-info/entry_points.txt
dblinter-0.5.6.dist-info/licenses/LICENCE.md
dblinter-0.5.6.dist-info/RECORD
