Metadata-Version: 2.4
Name: dblinter
Version: 0.5.6
Summary: A static analysis tool for postgresql databases
License: Apache-2.0
License-File: LICENCE.md
Keywords: postgresql,static analysis,sonar,sarif,code quality,sql,database
Author: Stephane Defenin
Author-email: stephane.defenin@gmail.com
Requires-Python: >=3.12,<4.0
Classifier: Intended Audience :: Developers
Classifier: License :: OSI Approved :: Apache Software License
Classifier: Operating System :: OS Independent
Classifier: Programming Language :: Python :: 3
Classifier: Programming Language :: Python :: 3.12
Classifier: Programming Language :: Python :: 3.13
Classifier: Programming Language :: Python :: 3.14
Classifier: Topic :: Software Development :: Build Tools
Classifier: Topic :: Software Development :: Quality Assurance
Classifier: Topic :: Software Development :: Testing
Classifier: Topic :: Utilities
Requires-Dist: google-cloud-storage (>=3.2.0,<4.0.0)
Requires-Dist: jschema-to-python (>=1.2.3,<2.0.0)
Requires-Dist: psycopg2-binary (>=2.9.10,<3.0.0)
Requires-Dist: pydantic (>=2.11.7,<3.0.0)
Requires-Dist: pydantic-yaml (>=1.5.1,<2.0.0)
Requires-Dist: pyyaml (>=6.0,<7.0)
Requires-Dist: rich (>=13.9.4,<14.0.0)
Requires-Dist: sarif-om (>=1.0.4,<2.0.0)
Requires-Dist: typer
Requires-Dist: types-pyyaml (>=6.0.12.20250516,<7.0.0.0)
Project-URL: Repository, https://github.com/decathlon/dblinter
